smsir/__init__.py
smsir/customerclub.py
smsir/sms.py
smsir/token.py
smsir-1.0.5.dist-info/LICENSE
smsir-1.0.5.dist-info/METADATA
smsir-1.0.5.dist-info/WHEEL
smsir-1.0.5.dist-info/top_level.txt
smsir-1.0.5.dist-info/RECORD
