Metadata-Version: 2.1
Name: smsir
Version: 1.0.5
Summary: manage message in www.sms.ir
Home-page: https://github.com/rahimaee/smsir.git
Author: mohammad reza rahimaee
Author-email: mohammad.rahimaee@gmail.com
License: UNKNOWN
Project-URL: Bug Tracker, https://github.com/rahimaee/smsir/issues
Keywords: sms.ir,smsir_python,sms.ir pip
Platform: UNKNOWN
Classifier: Programming Language :: Python :: 3
Classifier: License :: OSI Approved :: MIT License
Classifier: Operating System :: OS Independent
Requires-Python: >=3.7
License-File: LICENSE
Requires-Dist: requests
Requires-Dist: certifi
Requires-Dist: charset-normalizer
Requires-Dist: idna
Requires-Dist: urllib3
